<Personalinformations>
	<Employee>
		<id>1</id>
		<name>John Doe</name>
		<Address>H# 38, R#3, Banani, Dhaka </Address>
		<Department>Sales</Department>
		<salary>$20000</salary>
	</Employee>

	<Employee>
		<id>2</id>
		<name>Mark Zuckerberg</name>
		<Address> Flat# A/1, H# 20, R#18, Mirpur, Dhaka </Address>
		<Department>Accounts</Department>
		<salary>$12000</salary>
	</Employee>

	<Employee>
		<id>3</id>
		<name>Ala Voski</name>
		<Address>H# 38, R#3, Motijheel </Address>
		<Department>Human Resource</Department>
		<salary>$30000</salary>
	</Employee>
</Personalinformations>